{
  "$schema": "https://ui.shadcn.com/schema/registry-item.json",
  "name": "hero-section-v2",
  "type": "registry:block",
  "title": "Hero Section V2",
  "description": "An editorial-style hero with asymmetric layout, serif display typography, and diagonal accents",
  "dependencies": [],
  "registryDependencies": [
    "button"
  ],
  "files": [
    {
      "path": "registry/new-york/blocks/hero-section/hero-section-v2/page.tsx",
      "content": "import { HeroSectionV2 } from \"../hero-section-v2\"\r\n\r\nexport default function Page() {\r\n    return <HeroSectionV2 />\r\n}\r\n",
      "type": "registry:page",
      "target": "app/hero-section-v2/page.tsx"
    },
    {
      "path": "registry/new-york/blocks/hero-section/hero-section-v2.tsx",
      "content": "\"use client\"\n\nimport { useState } from \"react\"\nimport \"./hero-section-v2.css\"\nimport { cn } from \"@/lib/utils\"\nimport { Button } from \"@/components/ui/button\"\n\nconst tabs = [\n    \"Lorem Ipsum\",\n    \"Dolor Sit\",\n    \"Amet Consec\",\n    \"Adipiscing\",\n    \"Elit Sed\",\n]\n\nconst PLACEHOLDER_IMAGE =\n    \"https://images.unsplash.com/photo-1604076850742-4c7221f3101b?q=80&w=1887&auto=format&fit=crop&ixlib=rb-4.1.0&ixid=M3wxMjA3fDB8MHxwaG90by1wYWdlfHx8fGVufDB8fHx8fA%3D%3D\"\n\nfunction PanelImage({\n    src = PLACEHOLDER_IMAGE,\n    alt,\n    className,\n}: {\n    src?: string\n    alt?: string\n    className?: string\n}) {\n    return (\n        <div className={cn(\"hs2-img-wrap\", className)}>\n            <div className=\"hs2-img-overlay\" aria-hidden=\"true\" />\n            <img\n                src={src}\n                alt={alt ?? \"Placeholder\"}\n                className=\"hs2-img\"\n            />\n        </div>\n    )\n}\n\n/* Tab 0 — Text left, image right */\nfunction PanelHero() {\n    return (\n        <div className=\"hs2-panel hs2-panel-split\">\n            <div className=\"hs2-panel-col\" style={{ gap: \"0.625rem\", justifyContent: \"center\" }}>\n                <span className=\"hs2-panel-badge\">Lorem</span>\n                <h3 className=\"hs2-panel-heading\">Lorem ipsum dolor sit amet</h3>\n                <p className=\"hs2-panel-text\">\n                    Sed do eiusmod tempor incididunt ut labore et dolore magna aliqua.\n                    Ut enim ad minim veniam, quis nostrud exercitation.\n                </p>\n            </div>\n            <PanelImage className=\"hs2-panel-image\" alt=\"Lorem ipsum\" />\n        </div>\n    )\n}\n\n/* Tab 1 — Image left, text right (reversed) */\nfunction PanelDashboard() {\n    return (\n        <div className=\"hs2-panel hs2-panel-split hs2-panel-reverse\">\n            <PanelImage className=\"hs2-panel-image\" alt=\"Dolor sit\" />\n            <div className=\"hs2-panel-col\" style={{ gap: \"0.625rem\", justifyContent: \"center\" }}>\n                <span className=\"hs2-panel-badge\">Dolor</span>\n                <h3 className=\"hs2-panel-heading\">Dolor sit amet consectetur</h3>\n                <p className=\"hs2-panel-text\">\n                    Ut enim ad minim veniam, quis nostrud exercitation ullamco\n                    laboris nisi ut aliquip ex ea commodo consequat.\n                </p>\n            </div>\n        </div>\n    )\n}\n\n/* Tab 2 — Text with bullet list left, image right */\nfunction PanelMedia() {\n    return (\n        <div className=\"hs2-panel hs2-panel-split\">\n            <div className=\"hs2-panel-col\" style={{ gap: \"0.625rem\", justifyContent: \"center\" }}>\n                <span className=\"hs2-panel-badge\">Amet</span>\n                <h3 className=\"hs2-panel-heading\">Amet consectetur adipiscing</h3>\n                <ul className=\"hs2-panel-list\">\n                    <li>Lorem ipsum dolor sit amet</li>\n                    <li>Consectetur adipiscing elit sed</li>\n                    <li>Eiusmod tempor incididunt labore</li>\n                </ul>\n            </div>\n            <PanelImage className=\"hs2-panel-image\" alt=\"Amet consec\" />\n        </div>\n    )\n}\n\n/* Tab 3 — Image left, large heading + text right */\nfunction PanelContent() {\n    return (\n        <div className=\"hs2-panel hs2-panel-split hs2-panel-reverse\">\n            <PanelImage className=\"hs2-panel-image\" alt=\"Adipiscing\" />\n            <div className=\"hs2-panel-col\" style={{ gap: \"0.5rem\", justifyContent: \"center\" }}>\n                <span className=\"hs2-panel-badge\">Adipiscing</span>\n                <h3 className=\"hs2-panel-heading hs2-panel-heading-lg\">Consectetur adipiscing elit</h3>\n                <p className=\"hs2-panel-text\">\n                    Quis nostrud exercitation ullamco laboris nisi ut aliquip\n                    ex ea commodo consequat duis aute irure dolor.\n                </p>\n            </div>\n        </div>\n    )\n}\n\n/* Tab 4 — Two stacked images left, text right */\nfunction PanelGallery() {\n    return (\n        <div className=\"hs2-panel hs2-panel-split\">\n            <div className=\"hs2-panel-duo\">\n                <PanelImage className=\"hs2-panel-duo-img\" alt=\"Elit sed 1\" />\n                <PanelImage className=\"hs2-panel-duo-img\" alt=\"Elit sed 2\" />\n            </div>\n            <div className=\"hs2-panel-col\" style={{ gap: \"0.625rem\", justifyContent: \"center\" }}>\n                <span className=\"hs2-panel-badge\">Elit</span>\n                <h3 className=\"hs2-panel-heading\">Elit sed do eiusmod tempor</h3>\n                <p className=\"hs2-panel-text\">\n                    Excepteur sint occaecat cupidatat non proident, sunt in culpa\n                    qui officia deserunt mollit anim id est laborum.\n                </p>\n            </div>\n        </div>\n    )\n}\n\nconst panels = [PanelHero, PanelDashboard, PanelMedia, PanelContent, PanelGallery]\n\nexport function HeroSectionV2({\n    className,\n    ...props\n}: React.ComponentProps<\"div\">) {\n    const [activeTab, setActiveTab] = useState(0)\n\n    const ActivePanel = panels[activeTab]\n\n    return (\n        <div className={cn(\"hs2-root\", className)} {...props}>\n            <div className=\"hs2-inner\">\n                {/* Hero Top — text row (title + description), then buttons */}\n                <div className=\"hs2-hero-top\">\n                    <div className=\"hs2-hero-text\">\n                        <h1 className=\"hs2-headline\">\n                            Lorem ipsum dolor sit amet\n                        </h1>\n                        <p className=\"hs2-description\">\n                            Lorem ipsum dolor sit amet, consectetur adipiscing elit. Sed\n                            do eiusmod tempor incididunt ut labore et dolore magna aliqua.\n                            Ut enim ad minim veniam, quis nostrud exercitation ullamco.\n                        </p>\n                    </div>\n                    <div className=\"hs2-actions\">\n                        <Button\n                            variant=\"default\"\n                            className=\"rounded-full hs2-btn-primary\"\n                        >\n                            Sign up\n                        </Button>\n                        <Button\n                            variant=\"outline\"\n                            className=\"rounded-full hs2-btn-secondary\"\n                        >\n                            Contact sales\n                        </Button>\n                    </div>\n                </div>\n\n                {/* Interactive Card */}\n                <div className=\"hs2-card\">\n                    {/* Tab Navigation */}\n                    <div className=\"hs2-tabs\">\n                        {tabs.map((tab, i) => (\n                            <button\n                                key={tab}\n                                className={cn(\n                                    \"hs2-tab\",\n                                    activeTab === i && \"hs2-tab-active\"\n                                )}\n                                onClick={() => setActiveTab(i)}\n                            >\n                                {tab}\n                            </button>\n                        ))}\n                    </div>\n\n                    {/* Card Content — image panels per tab */}\n                    <div className=\"hs2-card-content\">\n                        <ActivePanel />\n                    </div>\n                </div>\n            </div>\n        </div>\n    )\n}\n",
      "type": "registry:component",
      "target": "app/hero-section-v2.tsx"
    },
    {
      "path": "registry/new-york/blocks/hero-section/hero-section-v2.css",
      "content": "/* CSS Variables for Hero Section V2 */\r\n/* These variables are required for the component styles to work correctly */\r\n/* Import this file in your globals.css or app layout */\r\n\r\n/* Fonts — inherits --font-sans from next/font (globals.css) */\r\n\r\n/* ============================================\r\n   Hero Section V2 — Clean, modern, serif display heading,\r\n   pill buttons, warm interactive card,\r\n   tabbed image content\r\n   ============================================ */\r\n\r\n/* ── Root ────────────────────────────────────── */\r\n\r\n.hs2-root {\r\n  width: 100%;\r\n  position: relative;\r\n  background: var(--background);\r\n}\r\n\r\n/* ── Inner wrapper ───────────────────────────── */\r\n\r\n.hs2-inner {\r\n  position: relative;\r\n  z-index: 10;\r\n  display: flex;\r\n  flex-direction: column;\r\n  max-width: 72rem;\r\n  margin-inline: auto;\r\n  width: 100%;\r\n  padding: 4rem 1.25rem 0;\r\n}\r\n\r\n@media (min-width: 768px) {\r\n  .hs2-inner {\r\n    padding: 5rem 2rem 0;\r\n  }\r\n}\r\n\r\n@media (min-width: 1024px) {\r\n  .hs2-inner {\r\n    padding: 6rem 3rem 0;\r\n  }\r\n}\r\n\r\n/* ── Hero top — vertical stack: text row, then buttons ── */\r\n\r\n.hs2-hero-top {\r\n  display: flex;\r\n  flex-direction: column;\r\n  gap: 1.25rem;\r\n  margin-bottom: 2rem;\r\n}\r\n\r\n@media (min-width: 768px) {\r\n  .hs2-hero-top {\r\n    gap: 1.75rem;\r\n    margin-bottom: 3rem;\r\n  }\r\n}\r\n\r\n@media (min-width: 1024px) {\r\n  .hs2-hero-top {\r\n    gap: 2rem;\r\n    margin-bottom: 3.5rem;\r\n  }\r\n}\r\n\r\n/* ── Text row — title left, description right, top-aligned ── */\r\n\r\n.hs2-hero-text {\r\n  display: grid;\r\n  grid-template-columns: 1fr;\r\n  gap: 0.75rem;\r\n  align-items: start;\r\n}\r\n\r\n@media (min-width: 768px) {\r\n  .hs2-hero-text {\r\n    gap: 1.5rem;\r\n  }\r\n}\r\n\r\n@media (min-width: 1024px) {\r\n  .hs2-hero-text {\r\n    grid-template-columns: 1fr 1fr;\r\n    gap: 3rem;\r\n  }\r\n}\r\n\r\n/* ── Heading ─────────────────────────────────── */\r\n\r\n.hs2-headline {\r\n  font-family: var(--font-display);\r\n  font-size: clamp(2rem, 4.5vw, 3.25rem);\r\n  font-weight: 400;\r\n  line-height: 1.1;\r\n  letter-spacing: -0.015em;\r\n  color: var(--foreground);\r\n  margin: 0;\r\n}\r\n\r\n/* ── Description ─────────────────────────────── */\r\n\r\n.hs2-description {\r\n  font-family: var(--font-sans);\r\n  font-size: 0.875rem;\r\n  line-height: 1.65;\r\n  color: var(--muted-foreground);\r\n  max-width: 32rem;\r\n  margin: 0;\r\n}\r\n\r\n@media (min-width: 480px) {\r\n  .hs2-description {\r\n    font-size: 0.9375rem;\r\n    line-height: 1.7;\r\n  }\r\n}\r\n\r\n@media (min-width: 768px) {\r\n  .hs2-description {\r\n    font-size: 1rem;\r\n  }\r\n}\r\n\r\n/* ── CTA actions (below text row) ────────────── */\r\n\r\n.hs2-actions {\r\n  display: flex;\r\n  flex-wrap: wrap;\r\n  align-items: center;\r\n  gap: 0.75rem;\r\n}\r\n\r\n.hs2-btn-primary {\r\n  font-weight: 500;\r\n  padding-inline: 1.75rem;\r\n}\r\n\r\n.hs2-btn-secondary {\r\n  font-weight: 500;\r\n  padding-inline: 1.5rem;\r\n}\r\n\r\n/* ── Interactive card ────────────────────────── */\r\n\r\n.hs2-card {\r\n  background: var(--hs2-card-bg);\r\n  border-radius: 1rem;\r\n  padding: 1rem;\r\n  display: flex;\r\n  flex-direction: column;\r\n  gap: 1rem;\r\n  position: relative;\r\n  isolation: isolate;\r\n}\r\n\r\n.hs2-card::before {\r\n  content: \"\";\r\n  position: absolute;\r\n  inset: 0;\r\n  border-radius: inherit;\r\n  pointer-events: none;\r\n  z-index: 1;\r\n  opacity: 0.45;\r\n  filter: url(#hs2-grain);\r\n  background: url(\"data:image/svg+xml,%3Csvg viewBox='0 0 256 256' xmlns='http://www.w3.org/2000/svg'%3E%3Cfilter id='hs2-grain'%3E%3CfeTurbulence type='fractalNoise' baseFrequency='0.75' numOctaves='4' stitchTiles='stitch'/%3E%3C/filter%3E%3Crect width='100%25' height='100%25' filter='url(%23hs2-grain)'/%3E%3C/svg%3E\");\r\n  background-size: 180px 180px;\r\n  mix-blend-mode: overlay;\r\n}\r\n\r\n.dark .hs2-card::before {\r\n  opacity: 0.3;\r\n  mix-blend-mode: soft-light;\r\n}\r\n\r\n/* Fonts — inherits --font-sans and --font-display from next/font (globals.css) */\r\n\r\n:root {\r\n  /* Colors */\r\n  --hs2-card-bg: oklch(0.95 0.01 75 / 1);\r\n  --hs2-subcard-bg: var(--background);\r\n  --hs2-subcard-border: var(--border);\r\n}\r\n\r\n.dark {\r\n  /* Colors */\r\n  --hs2-card-bg: oklch(0.22 0.01 75 / 1);\r\n  --hs2-subcard-bg: oklch(0.18 0.005 75 / 1);\r\n  --hs2-subcard-border: oklch(0.30 0.01 75 / 1);\r\n}\r\n\r\n@media (min-width: 480px) {\r\n  .hs2-card {\r\n    border-radius: 1.125rem;\r\n    padding: 1.25rem;\r\n    gap: 1.25rem;\r\n  }\r\n}\r\n\r\n@media (min-width: 768px) {\r\n  .hs2-card {\r\n    border-radius: 1.25rem;\r\n    padding: 1.5rem;\r\n    gap: 1.5rem;\r\n  }\r\n}\r\n\r\n@media (min-width: 1024px) {\r\n  .hs2-card {\r\n    padding: 2rem;\r\n  }\r\n}\r\n\r\n/* ── Tab navigation ──────────────────────────── */\r\n\r\n.hs2-tabs {\r\n  display: flex;\r\n  align-items: center;\r\n  gap: 0.375rem;\r\n  justify-content: flex-start;\r\n  overflow-x: auto;\r\n  -webkit-overflow-scrolling: touch;\r\n  scrollbar-width: none;\r\n  -ms-overflow-style: none;\r\n}\r\n\r\n.hs2-tabs::-webkit-scrollbar {\r\n  display: none;\r\n}\r\n\r\n@media (min-width: 768px) {\r\n  .hs2-tabs {\r\n    justify-content: center;\r\n    overflow-x: visible;\r\n    flex-wrap: wrap;\r\n  }\r\n}\r\n\r\n.hs2-tab {\r\n  font-family: var(--font-sans);\r\n  font-size: 0.8125rem;\r\n  font-weight: 500;\r\n  color: var(--muted-foreground);\r\n  background: transparent;\r\n  border: 1px solid transparent;\r\n  border-radius: 9999px;\r\n  padding: 0.4375rem 0.875rem;\r\n  cursor: pointer;\r\n  transition: all 0.2s ease;\r\n  white-space: nowrap;\r\n  line-height: 1.4;\r\n  flex-shrink: 0;\r\n}\r\n\r\n.hs2-tab:hover {\r\n  color: var(--foreground);\r\n  background: var(--hs2-subcard-bg);\r\n}\r\n\r\n.hs2-tab-active {\r\n  color: var(--foreground);\r\n  background: var(--hs2-subcard-bg);\r\n  border-color: var(--hs2-subcard-border);\r\n  box-shadow: 0 1px 2px oklch(0 0 0 / 0.04);\r\n}\r\n\r\n@media (min-width: 768px) {\r\n  .hs2-tab {\r\n    font-size: 0.875rem;\r\n    padding: 0.5rem 1.125rem;\r\n  }\r\n}\r\n\r\n/* ── Card content wrapper — responsive height, centered ── */\r\n\r\n.hs2-card-content {\r\n  background: var(--hs2-subcard-bg);\r\n  border: 1px solid var(--hs2-subcard-border);\r\n  border-radius: 0.875rem;\r\n  padding: 1rem;\r\n  height: 16rem;\r\n  overflow: hidden;\r\n  max-width: 52rem;\r\n  margin-inline: auto;\r\n  width: 100%;\r\n}\r\n\r\n@media (min-width: 480px) {\r\n  .hs2-card-content {\r\n    padding: 1.25rem;\r\n    height: 18rem;\r\n  }\r\n}\r\n\r\n@media (min-width: 768px) {\r\n  .hs2-card-content {\r\n    padding: 1.5rem;\r\n    height: 20rem;\r\n  }\r\n}\r\n\r\n@media (min-width: 1024px) {\r\n  .hs2-card-content {\r\n    padding: 2rem;\r\n    height: 22rem;\r\n  }\r\n}\r\n\r\n/* ── Panel base ──────────────────────────────── */\r\n\r\n.hs2-panel {\r\n  display: flex;\r\n  flex-direction: column;\r\n  width: 100%;\r\n  height: 100%;\r\n}\r\n\r\n/* Split — two columns (text + image) */\r\n.hs2-panel-split {\r\n  gap: 1rem;\r\n}\r\n\r\n@media (min-width: 768px) {\r\n  .hs2-panel-split {\r\n    flex-direction: row;\r\n    align-items: stretch;\r\n    gap: 1.25rem;\r\n  }\r\n}\r\n\r\n/* Reverse — image left, text right on desktop */\r\n@media (min-width: 768px) {\r\n  .hs2-panel-reverse {\r\n    flex-direction: row;\r\n  }\r\n}\r\n\r\n/* Bullet list inside panels */\r\n.hs2-panel-list {\r\n  list-style: none;\r\n  padding: 0;\r\n  margin: 0;\r\n  display: flex;\r\n  flex-direction: column;\r\n  gap: 0.375rem;\r\n}\r\n\r\n.hs2-panel-list li {\r\n  font-family: var(--font-sans);\r\n  font-size: 0.8125rem;\r\n  line-height: 1.55;\r\n  color: var(--muted-foreground);\r\n  padding-left: 1rem;\r\n  position: relative;\r\n}\r\n\r\n.hs2-panel-list li::before {\r\n  content: \"\";\r\n  position: absolute;\r\n  left: 0;\r\n  top: 0.5em;\r\n  width: 5px;\r\n  height: 5px;\r\n  border-radius: 50%;\r\n  background: var(--muted-foreground);\r\n  opacity: 0.45;\r\n}\r\n\r\n/* Large heading variant */\r\n.hs2-panel-heading-lg {\r\n  font-size: 1.25rem;\r\n  letter-spacing: -0.02em;\r\n}\r\n\r\n@media (min-width: 768px) {\r\n  .hs2-panel-heading-lg {\r\n    font-size: 1.5rem;\r\n  }\r\n}\r\n\r\n/* Duo — two stacked images in a column */\r\n.hs2-panel-duo {\r\n  display: flex;\r\n  flex-direction: column;\r\n  gap: 0.5rem;\r\n  flex: 1;\r\n  min-width: 0;\r\n  min-height: 0;\r\n}\r\n\r\n.hs2-panel-duo-img {\r\n  flex: 1;\r\n  min-height: 0;\r\n  border-radius: 0.375rem;\r\n}\r\n\r\n@media (max-width: 767px) {\r\n  .hs2-panel-duo {\r\n    display: none;\r\n  }\r\n}\r\n\r\n/* Stack — vertical flow */\r\n.hs2-panel-stack {\r\n  gap: 0.625rem;\r\n}\r\n\r\n/* Column inside split panels */\r\n.hs2-panel-col {\r\n  display: flex;\r\n  flex-direction: column;\r\n  flex: 1;\r\n  min-width: 0;\r\n}\r\n\r\n/* Image placeholder inside split panels */\r\n.hs2-panel-image {\r\n  width: 100%;\r\n  flex-shrink: 0;\r\n  flex: 1;\r\n  min-height: 0;\r\n}\r\n\r\n@media (max-width: 767px) {\r\n  .hs2-panel-image {\r\n    display: none;\r\n  }\r\n}\r\n\r\n/* ── Image wrapper ────────────────────────────── */\r\n\r\n.hs2-img-wrap {\r\n  overflow: hidden;\r\n  border-radius: 0.5rem;\r\n  position: relative;\r\n  background: var(--muted);\r\n}\r\n\r\n.hs2-img-overlay {\r\n  position: absolute;\r\n  inset: 0;\r\n  z-index: 2;\r\n  background: oklch(0.55 0.06 75);\r\n  opacity: 0.45;\r\n  mix-blend-mode: color;\r\n}\r\n\r\n.dark .hs2-img-overlay {\r\n  background: oklch(0.45 0.05 75);\r\n  opacity: 0.5;\r\n}\r\n\r\n.hs2-img {\r\n  position: relative;\r\n  z-index: 1;\r\n  width: 100%;\r\n  height: 100%;\r\n  object-fit: cover;\r\n  display: block;\r\n  filter: brightness(0.85) saturate(0.7);\r\n}\r\n\r\n\r\n/* ── Panel content styles ────────────────────── */\r\n\r\n.hs2-panel-badge {\r\n  font-family: var(--font-sans);\r\n  font-size: 0.6875rem;\r\n  font-weight: 600;\r\n  text-transform: uppercase;\r\n  letter-spacing: 0.06em;\r\n  color: var(--muted-foreground);\r\n}\r\n\r\n.hs2-panel-heading {\r\n  font-family: var(--font-sans);\r\n  font-size: 1rem;\r\n  font-weight: 600;\r\n  line-height: 1.3;\r\n  color: var(--foreground);\r\n  margin: 0;\r\n}\r\n\r\n.hs2-panel-text {\r\n  font-family: var(--font-sans);\r\n  font-size: 0.8125rem;\r\n  line-height: 1.55;\r\n  color: var(--muted-foreground);\r\n  margin: 0;\r\n}\r\n\r\n\r\n/* ── Entry animations — staggered, gentle ────── */\r\n\r\n@keyframes hs2-fade-up {\r\n  from {\r\n    opacity: 0;\r\n    transform: translateY(18px);\r\n  }\r\n  to {\r\n    opacity: 1;\r\n    transform: translateY(0);\r\n  }\r\n}\r\n\r\n.hs2-hero-top {\r\n  animation: hs2-fade-up 0.6s cubic-bezier(0.22, 1, 0.36, 1) 0.05s both;\r\n}\r\n\r\n.hs2-actions {\r\n  animation: hs2-fade-up 0.55s cubic-bezier(0.22, 1, 0.36, 1) 0.15s both;\r\n}\r\n\r\n.hs2-card {\r\n  animation: hs2-fade-up 0.65s cubic-bezier(0.22, 1, 0.36, 1) 0.2s both;\r\n}\r\n\r\n/* ── Reduced motion ──────────────────────────── */\r\n\r\n@media (prefers-reduced-motion: reduce) {\r\n  .hs2-hero-top,\r\n  .hs2-actions,\r\n  .hs2-card {\r\n    animation: none;\r\n  }\r\n}\r\n",
      "type": "registry:component",
      "target": "app/hero-section-v2.css"
    }
  ]
}